strsync/__init__.py
strsync/__main__.py
strsync/lc_ios9.tsv
strsync/strsparser.py
strsync/strsync.py
strsync-1.1.3.dist-info/DESCRIPTION.rst
strsync-1.1.3.dist-info/METADATA
strsync-1.1.3.dist-info/RECORD
strsync-1.1.3.dist-info/WHEEL
strsync-1.1.3.dist-info/entry_points.txt
strsync-1.1.3.dist-info/metadata.json
strsync-1.1.3.dist-info/top_level.txt
