Metadata-Version: 2.0
Name: strsync
Version: 1.1.3
Summary: strsync - Automatically translate and synchronize localizable resource files from defined base language for Xcode.
Home-page: https://github.com/metasmile/strsync
Author: Metasmile @ StellarStep, Inc.
Author-email: cyrano905@gmail.com
License: MIT
Keywords: translation microsoft strsync strings localizable l10n i18n ios xcode osx mac
Platform: UNKNOWN
Classifier: Development Status :: 5 - Production/Stable
Classifier: Intended Audience :: Developers
Classifier: License :: OSI Approved :: MIT License
Classifier: Natural Language :: English
Classifier: Operating System :: OS Independent
Classifier: Topic :: Software Development :: Internationalization
Classifier: Topic :: Utilities
Classifier: Programming Language :: Python :: 3
Classifier: Programming Language :: Python :: 2
Requires-Dist: chardet
Requires-Dist: colorama
Requires-Dist: fuzzywuzzy
Requires-Dist: microsofttranslator
Requires-Dist: requests (>=1.2.3)
Requires-Dist: six
